setup.cfg
setup.py
tgext/__init__.py
tgext.less.egg-info/PKG-INFO
tgext.less.egg-info/SOURCES.txt
tgext.less.egg-info/dependency_links.txt
tgext.less.egg-info/entry_points.txt
tgext.less.egg-info/namespace_packages.txt
tgext.less.egg-info/not-zip-safe
tgext.less.egg-info/requires.txt
tgext.less.egg-info/top_level.txt
tgext/less/__init__.py
tgext/less/jinja.py
tgext/less/middleware.py