Metadata-Version: 1.0
Name: tgext.less
Version: 0.3.1
Summary: LESS middleware for TurboGears2
Home-page: http://bitbucket.org/clsdaniel/tgext.less
Author: Carlos Daniel Ruvalcaba Valenzuela
Author-email: clsdaniel@gmail.com
License: MIT
Keywords: turbogears2.extension LESS WSGI jinja2.extension
Platform: UNKNOWN
Classifier: Environment :: Web Environment
Classifier: Topic :: Software Development :: Libraries :: Python Modules
Classifier: Framework :: TurboGears
